LICENSE
MANIFEST.in
README.rst
setup.cfg
setup.py
versioneer.py
pymt_landlab/__init__.py
pymt_landlab/_version.py
pymt_landlab/bmi.py
pymt_landlab.egg-info/PKG-INFO
pymt_landlab.egg-info/SOURCES.txt
pymt_landlab.egg-info/dependency_links.txt
pymt_landlab.egg-info/entry_points.txt
pymt_landlab.egg-info/top_level.txt
pymt_landlab/data/DepthDependentDiffuser/api.yaml
pymt_landlab/data/DepthDependentDiffuser/depth_dependent_diffuser.yaml
pymt_landlab/data/DepthDependentDiffuser/info.yaml
pymt_landlab/data/DepthDependentDiffuser/parameters.yaml
pymt_landlab/data/DepthDependentDiffuser/run.yaml
pymt_landlab/data/ExponentialWeatherer/api.yaml
pymt_landlab/data/ExponentialWeatherer/exponential_weatherer.yaml
pymt_landlab/data/ExponentialWeatherer/info.yaml
pymt_landlab/data/ExponentialWeatherer/parameters.yaml
pymt_landlab/data/ExponentialWeatherer/run.yaml
pymt_landlab/data/Flexure/api.yaml
pymt_landlab/data/Flexure/flexure.yaml
pymt_landlab/data/Flexure/info.yaml
pymt_landlab/data/Flexure/parameters.yaml
pymt_landlab/data/Flexure/run.yaml
pymt_landlab/data/FlowAccumulator/api.yaml
pymt_landlab/data/FlowAccumulator/flow_accumulator.yaml
pymt_landlab/data/FlowAccumulator/info.yaml
pymt_landlab/data/FlowAccumulator/parameters.yaml
pymt_landlab/data/FlowAccumulator/run.yaml
pymt_landlab/data/FlowDirectorD8/api.yaml
pymt_landlab/data/FlowDirectorD8/flow_director_d8.yaml
pymt_landlab/data/FlowDirectorD8/info.yaml
pymt_landlab/data/FlowDirectorD8/parameters.yaml
pymt_landlab/data/FlowDirectorD8/run.yaml
pymt_landlab/data/FlowDirectorDINF/api.yaml
pymt_landlab/data/FlowDirectorDINF/flow_director_dinf.yaml
pymt_landlab/data/FlowDirectorDINF/info.yaml
pymt_landlab/data/FlowDirectorDINF/parameters.yaml
pymt_landlab/data/FlowDirectorDINF/run.yaml
pymt_landlab/data/FlowDirectorSteepest/api.yaml
pymt_landlab/data/FlowDirectorSteepest/flow_director_steepest.yaml
pymt_landlab/data/FlowDirectorSteepest/info.yaml
pymt_landlab/data/FlowDirectorSteepest/parameters.yaml
pymt_landlab/data/FlowDirectorSteepest/run.yaml
pymt_landlab/data/FlowRouter/api.yaml
pymt_landlab/data/FlowRouter/flow_router.yaml
pymt_landlab/data/FlowRouter/info.yaml
