Metadata-Version: 1.0
Name: pymt-landlab
Version: 0.3.0
Summary: PyMT plugin for landlab
Home-page: UNKNOWN
Author: Eric Hutton
Author-email: UNKNOWN
License: UNKNOWN
Platform: UNKNOWN
